{
  "quiz_title": "數位防詐高手挑戰賽",
  "questions": [
    {
      "id": 1,
      "category": "網購與物流",
      "type": "fraud",
      "question": "收到簡訊：『您的包裹配送地址不全，請點擊連結 (bit.ly/post-service) 重新輸入資料並付 20 元手續費』。",
      "options": ["點連結補齊資料並刷卡", "不點連結，去官網或下載官方 APP 查狀態"],
      "answer": 1,
      "explanation": "物流公司不會用簡訊要求你「輸入信用卡號」來更改地址，這是常見的釣魚手段。"
    },
    {
      "id": 2,
      "category": "網購與物流",
      "type": "real",
      "question": "收到簡訊：『您訂購的商品已抵達 7-11 門市，請於三日內憑證件取貨』。簡訊內沒有任何網址連結。",
      "options": ["這是詐騙，絕對不去取貨", "確認自己有無購物，再去取貨"],
      "answer": 1,
      "explanation": "不帶連結、僅通知取貨的簡訊通常是正常的。但領取前仍要確認是否為自己訂購的商品，避免「幽靈包裹」。"
    },
    {
      "id": 3,
      "category": "網購與物流",
      "type": "fraud",
      "question": "在臉書看到：『百貨公司結束營業，原價三萬元的相機現在只要 1500 元』，強調貨到付款，限時搶購。",
      "options": ["價格太便宜了，趕快下單", "這是典型的一頁式廣告詐騙，不予理會"],
      "answer": 1,
      "explanation": "低於市價過多的商品極具風險，一頁式廣告常缺乏聯絡資訊，貨到付款也可能拿到垃圾。"
    },
    {
      "id": 4,
      "category": "網購與物流",
      "type": "fraud",
      "question": "接到自稱電商客服電話：『抱歉系統出錯，將您設為批發商會重複扣款 12 次，請去 ATM 操作取消。』",
      "options": ["立刻去 ATM 照指示操作", "掛斷電話，ATM 只有轉帳功能沒有解除設定功能"],
      "answer": 1,
      "explanation": "這是經典的「解除分期付款」詐騙，ATM 完全沒有解除設定或驗證身分的功能。"
    },
    {
      "id": 5,
      "category": "網購與物流",
      "type": "real",
      "question": "網購官網發出推播通知：『本期會員紅利即將到期，請登入官網兌換』，網址為該公司的官方網域。",
      "options": ["自行開啟官網確認紅利資訊", "覺得只要是網址都是騙人的"],
      "answer": 0,
      "explanation": "官方網域的通知通常是安全的，但保險起見建議「自行開啟官方網頁」而非直接點選來源不明的連結。"
    },
    {
      "id": 6,
      "category": "網購與物流",
      "type": "fraud",
      "question": "賣家私訊你：『為了幫您省平台手續費，我們加 LINE 私下匯款，我再給你 9 折優惠。』",
      "options": ["答應私下交易省錢", "拒絕，只透過平台保障交易安全"],
      "answer": 1,
      "explanation": "私下交易會失去平台保障，一旦匯款後賣家消失，你將求助無門。"
    },
    {
      "id": 7,
      "category": "通訊與社群",
      "type": "fraud",
      "question": "好友在 LINE 傳訊息：『我手機懷了，可以幫我收個簡訊認證碼並傳給我嗎？』",
      "options": ["打電話給本人確認", "立刻幫他收並告知驗證碼"],
      "answer": 0,
      "explanation": "驗證碼就是帳號的鑰匙，一旦給出，你的帳號就會被盜走。"
    },
    {
      "id": 8,
      "category": "通訊與社群",
      "type": "real",
      "question": "長輩在 LINE 群組傳送一張長輩圖，寫著：『天氣轉涼，記得多穿衣服。』",
      "options": ["覺得是詐騙連結，立刻舉報", "這是正常的問候，回個貼圖即可"],
      "answer": 1,
      "explanation": "單純的圖片或文字問候是社交常態，不涉及個資或金錢通常是安全的。"
    },
    {
      "id": 9,
      "category": "通訊與社群",
      "type": "fraud",
      "question": "收到陌生人的 LINE 好友邀請，大頭貼是美女/帥哥，寫著：『我是某某證券助理，有飆股分享。』",
      "options": ["加入看看有沒有賺錢機會", "直接封鎖並檢舉"],
      "answer": 1,
      "explanation": "這是典型的投資詐騙開頭，專門誘導民眾加入詐騙群組進行假投資。"
    },
    {
      "id": 10,
      "category": "通訊與社群",
      "type": "fraud",
      "question": "剛認識三天的交友對象說：『我最近在玩這款投資 App，每天賺三千，你要不要跟著我操作？』",
      "options": ["為了增進感情，投一點點試試", "這是「殺豬盤」詐騙，拒絕參與"],
      "answer": 1,
      "explanation": "先建立情感信任再誘導投資是典型詐騙，千萬不要在不明平台投入資金。"
    },
    {
      "id": 11,
      "category": "通訊與社群",
      "type": "real",
      "question": "好友在 FB 發文：『這間拉麵店超好吃的，給你參考 (Google Maps 網址)』。",
      "options": ["確認網域為 maps.app.goo.gl 後可點看評價", "只要是網址一律不點"],
      "answer": 0,
      "explanation": "識別知名且正確的官方網域（如 Google Maps）是防詐的基礎，不需要過度恐慌。"
    },
    {
      "id": 12,
      "category": "通訊與社群",
      "type": "fraud",
      "question": "收到簡訊：『您的 LINE 帳號異常，請點此連結 (line-login.me) 重新驗證，否則將停權。』",
      "options": ["點進去趕快輸入帳密驗證", "不點連結，這是釣魚網站"],
      "answer": 1,
      "explanation": "官方不會透過簡訊要求你在非官方網域輸入密碼，這是在盜取你的登入權限。"
    },
    {
      "id": 13,
      "category": "金融投資",
      "type": "fraud",
      "question": "接到自稱銀行客服：『您的信用卡在國外被盜刷，請提供卡號後三碼與手機簡訊碼供核對。』",
      "options": ["為了止付，趕快告訴對方", "掛斷電話，自行撥打信用卡背面的銀行電話"],
      "answer": 1,
      "explanation": "銀行客服不會主動要求你告知「簡訊驗證碼」或「卡號後三碼」，那是交易的最後關鍵資料。"
    },
    {
      "id": 14,
      "category": "金融投資",
      "type": "real",
      "question": "銀行 App 跳出推播訊息：『本月信用卡帳單已出帳，應繳總金額為 5,000 元，請按時繳納。』",
      "options": ["這是詐騙，絕對不繳錢", "進入 App 確認帳單明細並繳款"],
      "answer": 1,
      "explanation": "透過官方 App 推播的繳款提醒是正常流程，只要不隨意點擊外部傳來的奇怪連結即可。"
    },
    {
      "id": 15,
      "category": "金融投資",
      "type": "fraud",
      "question": "YouTube 廣告宣稱：『我是某知名理財導師，保證獲利 20%，零風險，現在加入領取密碼袋。』",
      "options": ["保證獲利太吸引人了，加入看看", "保證獲利、零風險就是詐騙的關鍵字"],
      "answer": 1,
      "explanation": "投資一定有風險，任何宣稱「保證獲利」且「零風險」的資訊 100% 是詐騙。"
    },
    {
      "id": 16,
      "category": "金融投資",
      "type": "fraud",
      "question": "收到郵件：『您的銀行帳戶暫時凍結，請點此連結輸入身分證字號解鎖。』網址看起來像官網但尾碼不對。",
      "options": ["趕快點進去解鎖", "不要點擊，這是釣魚郵件"],
      "answer": 1,
      "explanation": "銀行不會透過郵件連結要求輸入身分證字號等高度敏感資訊。"
    },
    {
      "id": 17,
      "category": "金融投資",
      "type": "real",
      "question": "接到銀行電話：『您好，本行目前有提供優質客戶低利貸款，有需要參考看看嗎？』過程中無求個資。",
      "options": ["拒絕並掛斷，這也是詐騙", "若有需求可聽聽看，或去實體分行詢問"],
      "answer": 1,
      "explanation": "銀行電話行銷是常見業務，只要不透過電話提供個資或密碼，通常是單純的推廣。"
    },
    {
      "id": 18,
      "category": "金融投資",
      "type": "fraud",
      "question": "收到簡訊：『恭喜獲得紓困貸款額度 50 萬，利率只要 0.1%，點擊連結由專員為您服務。』",
      "options": ["點連結申請，利率很划算", "這是假貸款詐騙，旨在騙取手續費或個人帳戶"],
      "answer": 1,
      "explanation": "非官方管道的「高額低利」貸款廣告，通常是為了騙取你的個資或存款帳戶。"
    },
    {
      "id": 19,
      "category": "假冒機構",
      "type": "fraud",
      "question": "接到自稱檢察官電話：『你涉及洗錢，請將現金交給自稱法務部派來的專員進行監管。』",
      "options": ["配合監管以證明清白", "直接掛斷，警察不會在電話中要求交錢"],
      "answer": 1,
      "explanation": "政府機關絕對不會要求民眾「交付現金」或「監管帳戶」，這是假檢警詐騙的核心。"
    },
    {
      "id": 20,
      "category": "假冒機構",
      "type": "fraud",
      "question": "接到自動語音電話：『健保局通知，您的健保卡異常使用將被停卡，請按 9 由專員處理。』",
      "options": ["趕快按 9 詢問詳情", "掛斷電話，這是不實資訊"],
      "answer": 1,
      "explanation": "健保局不會使用「自動語音」電話通知民眾，也不會在電話中要求轉接警察局。"
    },
    {
      "id": 21,
      "category": "假冒機構",
      "type": "real",
      "question": "郵差按門鈴：『某某先生，有一封您的掛號信，請準備印章或簽名簽收。』",
      "options": ["這是詐騙，絕對不開門", "準備印章簽收掛號信"],
      "answer": 1,
      "explanation": "實體掛號信是正常的政府與民眾通訊方式，簽收信件本身不具備詐騙風險。"
    },
    {
      "id": 22,
      "category": "假冒機構",
      "type": "fraud",
      "question": "接到電話自稱是電力公司：『您欠費三個月，若不立即轉帳或刷卡，將在兩小時內斷電。』",
      "options": ["立刻照指示轉帳", "掛斷電話，親自去台電櫃檯或官網查詢"],
      "explanation": "台電不會在電話中要求轉帳。遇到欠費通知，應掛斷電話並自行查證。",
      "answer": 1
    },
    {
      "id": 23,
      "category": "假冒機構",
      "type": "real",
      "question": "里長廣播：『各位里民大家好，明天早上將進行全里登革熱噴藥作業，請做好準備。』",
      "options": ["這是詐騙廣播，不予理會", "依照廣播內容做好防疫準備"],
      "answer": 1,
      "explanation": "地方里長廣播是社區通知的正常管道，旨在維護公共安全。"
    },
    {
      "id": 24,
      "category": "假冒機構",
      "type": "fraud",
      "question": "收到電子郵件：『我是國稅局，您有一筆退稅尚未領取，請點擊連結輸入銀行帳號以撥款。』",
      "options": ["輸入帳號領錢", "退稅不會透過郵件連結辦理"],
      "answer": 1,
      "explanation": "退稅通常是透過申報時填寫的帳戶或寄送支票，不會透過不明郵件連結要求輸入個資。"
    },
    {
      "id": 25,
      "category": "生活求職",
      "type": "fraud",
      "question": "網頁彈出視窗：『恭喜！您中獎了，獲得最新 iPhone，僅需支付 100 元國際運費。』",
      "options": ["支付小額運費換手機", "關閉視窗，這是在騙信用卡號碼"],
      "answer": 1,
      "explanation": "天下沒有白吃的午餐，這是為了獲取你的信用卡資訊進行後續盜刷。"
    },
    {
      "id": 26,
      "category": "生活求職",
      "type": "fraud",
      "question": "求職廣告：『在家工作、代收貨款、每天現領 3000 元，只需提供銀行帳號供轉帳使用。』",
      "options": ["剛好缺錢，加入看看", "這是洗錢陷阱，帳戶會變警示帳戶"],
      "answer": 1,
      "explanation": "要求提供帳號來「轉收金流」的工作大多是詐騙集團在找「人頭帳戶」，會讓你背負法律責任。"
    },
    {
      "id": 27,
      "category": "生活求職",
      "type": "fraud",
      "question": "接到陌生電話聲音很像朋友：『猜猜我是誰？我是你那個換了號碼的老同學啦！』",
      "options": ["隨便猜一個名字看是不是他", "掛斷電話，這就是「猜猜我是誰」詐騙"],
      "answer": 1,
      "explanation": "對方會利用你的心理暗示讓你自己說出名字，進而建立信任後借錢。"
    },
    {
      "id": 28,
      "category": "生活求職",
      "type": "real",
      "question": "去連鎖超市買東西，櫃檯店員問：『要不要報電話號碼累積會員點數？』",
      "options": ["這是詐騙個資，絕對不報", "如果我是會員，可報電話累積福利"],
      "answer": 1,
      "explanation": "實體商店的會員點數累積是正常服務，不涉及密碼或匯款通常是安全的。"
    },
    {
      "id": 29,
      "category": "生活求職",
      "type": "real",
      "question": "在餐廳用餐，店員指著桌上的 QR Code 說：『掃描這個可以線上點餐。』",
      "options": ["這是掃碼詐騙，絕對不掃", "可掃描進行點餐，並注意網址是否正常"],
      "answer": 1,
      "explanation": "QR Code 點餐已是現代餐飲常態，只要不跳轉到可疑的個資填寫頁面即可放心使用。"
    },
    {
      "id": 30,
      "category": "生活求職",
      "type": "fraud",
      "question": "路邊廣告：『掃描 QR Code 領取 500 元全聯禮券』，點開後要求填寫姓名、電話、地址與身分證字號。",
      "options": ["填寫資料領禮券", "這是誘騙個資，不予填寫"],
      "answer": 1,
      "explanation": "利用高額禮券誘導民眾填寫詳細個資是詐騙集團收集名單的手段。"
    }
  ]
}